nlfepy/__init__.py
nlfepy/constitutive/__init__.py
nlfepy/constitutive/constitutive.py
nlfepy/constitutive/constitutive_base.py
nlfepy/constitutive/crystal_plasticity.py
nlfepy/constitutive/get_constitutive_list.py
nlfepy/constitutive/isotropic.py
nlfepy/constitutive/j2flow.py
nlfepy/constitutive/variable.py
nlfepy/interface/__init__.py
nlfepy/interface/integral_equation.py
nlfepy/interface/pvw.py
nlfepy/interface/pvw_ul.py
nlfepy/io/__init__.py
nlfepy/io/vtu_reader.py
nlfepy/io/vtu_writer.py
nlfepy/material/__init__.py
nlfepy/material/aluminium.py
nlfepy/material/bcc.py
nlfepy/material/fcc.py
nlfepy/material/get_material_list.py
nlfepy/material/hcp.py
nlfepy/material/material.py
nlfepy/material/material_base.py
nlfepy/material/metal.py
nlfepy/mesh/__init__.py
nlfepy/mesh/mesh.py
nlfepy/shape/__init__.py
nlfepy/shape/hexa8.py
nlfepy/shape/nd2.py
nlfepy/shape/nd3.py
nlfepy/shape/nd4.py
nlfepy/shape/quad12.py
nlfepy/shape/quad16.py
nlfepy/shape/quad4.py
nlfepy/shape/quad8.py
nlfepy/shape/quad9.py
nlfepy/shape/shape_function.py
nlfepy/shape/shapef_util.py
nlfepy/shape/tet4.py
nlfepy/shape/tri10.py
nlfepy/shape/tri3.py
nlfepy/shape/tri6.py
nlfepy/util/__init__.py
nlfepy/util/calc_element_value.py
nlfepy/viewer/__init__.py
nlfepy/viewer/viewer.py
nlfepy/viewer/viewer2d.py
nlfepy/viewer/viewer3d.py
nlfepy/viewer/viewer_base.py
nlfepy-0.1.3.dist-info/LICENSE.txt
nlfepy-0.1.3.dist-info/METADATA
nlfepy-0.1.3.dist-info/WHEEL
nlfepy-0.1.3.dist-info/top_level.txt
nlfepy-0.1.3.dist-info/RECORD
