Metadata-Version: 2.1
Name: nlfepy
Version: 0.1.3
Summary: A simple finite element library for nonlinear analysis
Home-page: https://github.com/sKujirai/nlfepy
License: UNKNOWN
Keywords: sample,setuptools,development
Platform: UNKNOWN
Classifier: Development Status :: 3 - Alpha
Classifier: License :: OSI Approved :: MIT License
Classifier: Programming Language :: Python :: 3
Requires-Python: >=3.5
Requires-Dist: numpy
Requires-Dist: matplotlib
Requires-Dist: scipy
